pyuu/project/__init__.py
pyuu.project-0.0.2.dist-info/METADATA
pyuu.project-0.0.2.dist-info/WHEEL
pyuu.project-0.0.2.dist-info/top_level.txt
pyuu.project-0.0.2.dist-info/RECORD
